retraktarr/VERSION
retraktarr/__init__.py
retraktarr/config.py
retraktarr/retraktarr.py
retraktarr/api/__init__.py
retraktarr/api/arr.py
retraktarr/api/trakt.py
retraktarr-1.1.4.dist-info/LICENSE
retraktarr-1.1.4.dist-info/METADATA
retraktarr-1.1.4.dist-info/WHEEL
retraktarr-1.1.4.dist-info/entry_points.txt
retraktarr-1.1.4.dist-info/top_level.txt
retraktarr-1.1.4.dist-info/RECORD
