Metadata-Version: 2.1
Name: retraktarr
Version: 1.1.4
Summary: a simple Arr -> Trakt.tv list sync script
Home-page: https://github.com/zakkarry
Download-URL: https://github.com/zakkarry/retraktarr
Author: zakkarry
Author-email: zak@ary.dev
License: MIT
License-File: LICENSE
Requires-Dist: requests
